jsonschema2db.py
JSONSchema2DB-1.1.0.dist-info/LICENSE
JSONSchema2DB-1.1.0.dist-info/METADATA
JSONSchema2DB-1.1.0.dist-info/WHEEL
JSONSchema2DB-1.1.0.dist-info/top_level.txt
JSONSchema2DB-1.1.0.dist-info/RECORD
