Metadata-Version: 2.1
Name: JSONSchema2DB
Version: 1.1.0
Summary: Generate database tables from JSON schema
Home-page: https://better.engineering/jsonschema2db
Author: Erik Bernhardsson
Author-email: erikbern@better.com
License: MIT
Platform: UNKNOWN
Requires-Dist: change-case (>=0.5.2)
Requires-Dist: iso8601 (>=0.1.12)
Requires-Dist: psycopg2-binary (>=2.7.2)
